strix/__init__.py
strix/agents/StrixAgent/__init__.py
strix/agents/StrixAgent/strix_agent.py
strix/agents/StrixAgent/system_prompt.jinja
strix/agents/__init__.py
strix/agents/base_agent.py
strix/agents/state.py
strix/config/__init__.py
strix/config/config.py
strix/interface/__init__.py
strix/interface/assets/tui_styles.tcss
strix/interface/cli.py
strix/interface/main.py
strix/interface/streaming_parser.py
strix/interface/tool_components/__init__.py
strix/interface/tool_components/agent_message_renderer.py
strix/interface/tool_components/agents_graph_renderer.py
strix/interface/tool_components/base_renderer.py
strix/interface/tool_components/browser_renderer.py
strix/interface/tool_components/file_edit_renderer.py
strix/interface/tool_components/finish_renderer.py
strix/interface/tool_components/notes_renderer.py
strix/interface/tool_components/proxy_renderer.py
strix/interface/tool_components/python_renderer.py
strix/interface/tool_components/registry.py
strix/interface/tool_components/reporting_renderer.py
strix/interface/tool_components/scan_info_renderer.py
strix/interface/tool_components/terminal_renderer.py
strix/interface/tool_components/thinking_renderer.py
strix/interface/tool_components/todo_renderer.py
strix/interface/tool_components/user_message_renderer.py
strix/interface/tool_components/web_search_renderer.py
strix/interface/tui.py
strix/interface/utils.py
strix/llm/__init__.py
strix/llm/config.py
strix/llm/dedupe.py
strix/llm/llm.py
strix/llm/memory_compressor.py
strix/llm/utils.py
strix/runtime/__init__.py
strix/runtime/docker_runtime.py
strix/runtime/runtime.py
strix/runtime/tool_server.py
strix/skills/README.md
strix/skills/__init__.py
strix/skills/cloud/.gitkeep
strix/skills/coordination/root_agent.md
strix/skills/custom/.gitkeep
strix/skills/frameworks/fastapi.md
strix/skills/frameworks/nextjs.md
strix/skills/protocols/graphql.md
strix/skills/reconnaissance/.gitkeep
strix/skills/scan_modes/deep.md
strix/skills/scan_modes/quick.md
strix_agent-0.7.0.dist-info/METADATA
strix_agent-0.7.0.dist-info/WHEEL
strix_agent-0.7.0.dist-info/entry_points.txt
strix_agent-0.7.0.dist-info/licenses/LICENSE
strix_agent-0.7.0.dist-info/RECORD
